odoo/addons/account_move_line_menu/README.rst
odoo/addons/account_move_line_menu/__init__.py
odoo/addons/account_move_line_menu/__manifest__.py
odoo/addons/account_move_line_menu/i18n/account_move_line_menu.pot
odoo/addons/account_move_line_menu/i18n/fr.po
odoo/addons/account_move_line_menu/i18n/fr_FR.po
odoo/addons/account_move_line_menu/readme/CONTRIBUTORS.rst
odoo/addons/account_move_line_menu/readme/DESCRIPTION.rst
odoo/addons/account_move_line_menu/readme/USAGE.rst
odoo/addons/account_move_line_menu/static/description/icon.png
odoo/addons/account_move_line_menu/static/description/index.html
odoo/addons/account_move_line_menu/views/account_menu_views.xml
odoo_addon_account_move_line_menu-15.0.1.0.0.4.dist-info/METADATA
odoo_addon_account_move_line_menu-15.0.1.0.0.4.dist-info/WHEEL
odoo_addon_account_move_line_menu-15.0.1.0.0.4.dist-info/top_level.txt
odoo_addon_account_move_line_menu-15.0.1.0.0.4.dist-info/RECORD
