Metadata-Version: 2.1
Name: odoo-addon-account-move-line-menu
Version: 15.0.1.0.0.4
Summary: Adds a Journal Items menu
Home-page: https://github.com/OCA/account-financial-tools
Author: Open Source Integrators, Odoo Community Association (OCA)
Author-email: support@odoo-community.org
License: AGPL-3
Platform: UNKNOWN
Classifier: Programming Language :: Python
Classifier: Framework :: Odoo
Classifier: Framework :: Odoo :: 15.0
Classifier: License :: OSI Approved :: GNU Affero General Public License v3
Classifier: Development Status :: 4 - Beta
Requires-Python: >=3.8
Requires-Dist: odoo <15.1dev,>=15.0a
